Workbook

Sheet 00 · Method
B1: Hospitality / Food service
B2: The pack that shows margin, wages and cash before they hurt
B5: WHAT'S IN THE PACK
B6: Cash flow | C6: 12-month cash flow, plan and variance
B7: Margin | C7: Cost per portion and gross margin
B8: Stock | C8: Usage and loss value
B9: Rota | C9: Shifts and labour cost share
B10: Takings | C10: Daily takings and cash-up
B11: Training | C11: Training matrix — proof before a shift
B13: METHOD — HOW TO USE IT
B14: • MORNING: 3 priorities + opening
B15: • DURING THE DAY: takings + losses
B16: • EVENING: cash-up (till close)
B17: • WEEKLY: rota + margin
B18: • MONTHLY: cash flow + overview
B20: COLOURS
B21: Orange = you fill in · Blue = calculated automatically · White/grey = records
B23: ASSET-FORGE · v1.0 · 31/05/2026 · EU (Ireland) · Template — not financial or legal advice.

Sheet 01 · Day plan
B1: Day plan
B2: Three priorities and a clear schedule for the day
B5: Date
B6: Day
B8: TODAY'S 3 PRIORITIES
B9: 1
B10: 2
B11: 3
B13: DAY SCHEDULE
B14: Time | C14: Task | D14: Priority | E14: Done
B15: 07:00
B16: 08:00
B17: 09:00
B18: 10:00
B19: 11:00
B20: 12:00
B21: 13:00
B22: 14:00
B23: 15:00
B24: 16:00
B25: 17:00
B26: 18:00
... B37: Closing: premises secured

Sheet 02 · Overview
B1: Overview
B2: Automatic dashboard — pulls live figures from the other sheets
B6: ANNUAL REVENUE ↗ | F6: GROSS MARGIN ↗ | J6: NET PROFIT ↗
B7: =IFERROR('03 · Cash flow'!O13,0) | F7: =IFERROR('03 · Cash flow'!O18,0) | J7: =IFERROR('03 · Cash flow'!O26,0)
B11: REVENUE VS PLAN ↗ | F11: CLOSING CASH ↗ | J11: AVERAGE MARGIN ↗
B12: =IFERROR('03 · Cash flow'!Q13,0) | F12: =IFERROR('03 · Cash flow'!N29,0) | J12: =IFERROR('04 · Margin'!H30,0)
B16: LABOUR SHARE ↗
B17: =IFERROR('06 · Rota'!I31,0)
B20: INSIGHTS
B21: =IFERROR(IF('03 · Cash flow'!P13="","Revenue vs plan: enter the annual plan on the Cash flow sheet.","Revenue vs plan: "&TEXT('03 · Cash flow'!Q13,"#,##0 €")&" ("&TEXT('03 · Cash flow'!R13,"+0.0%;-0.0%")&") — "&IF('03 · Cash flow'!R13>=0,"ABOVE plan.","BELOW plan, check your main revenue source.")),"Revenue vs plan: no data yet.")
B22: =IFERROR("Net margin: "&TEXT('03 · Cash flow'!O26/'03 · Cash flow'!O13,"0.0%")&IF('03 · Cash flow'!O26/'03 · Cash flow'!O13>=0.1," — healthy."," — careful, low."),"Net margin: no data yet.")
B23: =IFERROR("Labour share: "&TEXT('06 · Rota'!I31,"0.0%")&IF('06 · Rota'!I31>0.35," — ABOVE the 35% target."," — fine."),"Labour share: no data yet.")
B24: =IFERROR("Loss/waste value: "&TEXT('05 · Stock'!I27,"#,##0.00 €")&".","Losses: no data yet.")
B25: =IFERROR("Items below target margin: "&TEXT('04 · Margin'!H31,"0")&".","Margin: no data yet.")
B26: =IFERROR("Till difference (year): "&TEXT('07 · Takings'!H40,"#,##0.00 €")&IF(ABS('07 · Takings'!H40)>1," — review."," — matches."),"Till: no data yet.")
B28: These figures update automatically as you fill in the other sheets.

Sheet 03 · Cash flow
B1: Cash flow
B2: 12-month cash flow, plan and variance
B5: Business name
B6: Year
B7: Fill in the orange cells (monthly actuals + annual plan). Totals, margin, profit, variance from plan and closing cash are calculated automatically.
B8: Item | C8: Jan | D8: Feb | E8: Mar | F8: Apr | G8: May | H8: Jun | I8: Jul | J8: Aug | K8: Sep | L8: Oct | M8: Nov | N8: Dec | O8: Year | P8: Plan (year) | Q8: Variance € | R8: Variance %
B9: REVENUE
B10: Food sales | O10: =SUM(C10:N10) | Q10: =IF(OR(O10="",P10=""),"",O10-P10) | R10: =IF(OR(P10="",P10=0,O10=""),"",(O10-P10)/P10)
B11: Drink sales | O11: =SUM(C11:N11) | Q11: =IF(OR(O11="",P11=""),"",O11-P11) | R11: =IF(OR(P11="",P11=0,O11=""),"",(O11-P11)/P11)
B12: Other income | O12: =SUM(C12:N12) | Q12: =IF(OR(O12="",P12=""),"",O12-P12) | R12: =IF(OR(P12="",P12=0,O12=""),"",(O12-P12)/P12)
B13: Total revenue | C13: =SUM(C10:C12) | D13: =SUM(D10:D12) | E13: =SUM(E10:E12) | F13: =SUM(F10:F12) | G13: =SUM(G10:G12) | H13: =SUM(H10:H12) | I13: =SUM(I10:I12) | J13: =SUM(J10:J12) | ... N13: =SUM(N10:N12) | O13: =SUM(C13:N13) | P13: =SUM(P10:P12) | Q13: =IF(OR(O13="",P13=""),"",O13-P13) | R13: =IF(OR(P13="",P13=0,O13=""),"",(O13-P13)/P13)
B14: COST OF SALES
B15: Food cost | O15: =SUM(C15:N15) | Q15: =IF(OR(O15="",P15=""),"",O15-P15) | R15: =IF(OR(P15="",P15=0,O15=""),"",(O15-P15)/P15)
B16: Drink cost | O16: =SUM(C16:N16) | Q16: =IF(OR(O16="",P16=""),"",O16-P16) | R16: =IF(OR(P16="",P16=0,O16=""),"",(O16-P16)/P16)
B17: Total costs | C17: =SUM(C15:C16) | D17: =SUM(D15:D16) | E17: =SUM(E15:E16) | F17: =SUM(F15:F16) | G17: =SUM(G15:G16) | H17: =SUM(H15:H16) | I17: =SUM(I15:I16) | J17: =SUM(J15:J16) | ... N17: =SUM(N15:N16) | O17: =SUM(C17:N17) | P17: =SUM(P15:P16) | Q17: =IF(OR(O17="",P17=""),"",O17-P17) | R17: =IF(OR(P17="",P17=0,O17=""),"",(O17-P17)/P17)
B18: GROSS MARGIN | C18: =C13-C17 | D18: =D13-D17 | E18: =E13-E17 | F18: =F13-F17 | G18: =G13-G17 | H18: =H13-H17 | I18: =I13-I17 | J18: =J13-J17 | ... N18: =N13-N17 | O18: =SUM(C18:N18) | P18: =P13-P17 | Q18: =IF(OR(O18="",P18=""),"",O18-P18) | R18: =IF(OR(P18="",P18=0,O18=""),"",(O18-P18)/P18)
B19: OVERHEADS
B20: Wages and staff | O20: =SUM(C20:N20) | Q20: =IF(OR(O20="",P20=""),"",O20-P20) | R20: =IF(OR(P20="",P20=0,O20=""),"",(O20-P20)/P20)
B21: Rent and rates | O21: =SUM(C21:N21) | Q21: =IF(OR(O21="",P21=""),"",O21-P21) | R21: =IF(OR(P21="",P21=0,O21=""),"",(O21-P21)/P21)
B22: Utilities | O22: =SUM(C22:N22) | Q22: =IF(OR(O22="",P22=""),"",O22-P22) | R22: =IF(OR(P22="",P22=0,O22=""),"",(O22-P22)/P22)
B23: Marketing | O23: =SUM(C23:N23) | Q23: =IF(OR(O23="",P23=""),"",O23-P23) | R23: =IF(OR(P23="",P23=0,O23=""),"",(O23-P23)/P23)
B24: Other overheads | O24: =SUM(C24:N24) | Q24: =IF(OR(O24="",P24=""),"",O24-P24) | R24: =IF(OR(P24="",P24=0,O24=""),"",(O24-P24)/P24)
B25: Total overheads | C25: =SUM(C20:C24) | D25: =SUM(D20:D24) | E25: =SUM(E20:E24) | F25: =SUM(F20:F24) | G25: =SUM(G20:G24) | H25: =SUM(H20:H24) | I25: =SUM(I20:I24) | J25: =SUM(J20:J24) | ... N25: =SUM(N20:N24) | O25: =SUM(C25:N25) | P25: =SUM(P20:P24) | Q25: =IF(OR(O25="",P25=""),"",O25-P25) | R25: =IF(OR(P25="",P25=0,O25=""),"",(O25-P25)/P25)
B26: NET PROFIT | C26: =C18-C25 | D26: =D18-D25 | E26: =E18-E25 | F26: =F18-F25 | G26: =G18-G25 | H26: =H18-H25 | I26: =I18-I25 | J26: =J18-J25 | ... N26: =N18-N25 | O26: =SUM(C26:N26) | P26: =P18-P25 | Q26: =IF(OR(O26="",P26=""),"",O26-P26) | R26: =IF(OR(P26="",P26=0,O26=""),"",(O26-P26)/P26)
B27: CASH
B28: Opening cash | D28: =C29 | E28: =D29 | F28: =E29 | G28: =F29 | H28: =G29 | I28: =H29 | J28: =I29 | K28: =J29 | ... N28: =M29 | O28: =C28
B29: Closing cash | C29: =C28+C26 | D29: =D28+D26 | E29: =E28+E26 | F29: =F28+F26 | G29: =G28+G26 | H29: =H28+H26 | I29: =I28+I26 | J29: =J28+J26 | ... N29: =N28+N26 | O29: =N29

Sheet 04 · Margin
B1: Margin
B2: Cost per portion and gross margin
B5: Business name
B6: Enter costs and target margin. The recommended price (ex VAT) is calculated; the real margin shows alongside.
B7: Dish / drink | C7: Size | D7: Cost € | E7: Target margin % | F7: Rec. price € | G7: Menu price € | H7: Real margin % | I7: Status
B8: Basket of house bread | F8: =IF(OR(D8="",E8=""),"",D8/(1-E8)) | H8: =IF(OR(G8="",D8=""),"",(G8-D8)/G8) | I8: =IF(OR(H8="",E8=""),"",IF(H8<E8,"LOW","OK"))
B9: Fish soup | F9: =IF(OR(D9="",E9=""),"",D9/(1-E9)) | H9: =IF(OR(G9="",D9=""),"",(G9-D9)/G9) | I9: =IF(OR(H9="",E9=""),"",IF(H9<E9,"LOW","OK"))
B10: Beef burger | F10: =IF(OR(D10="",E10=""),"",D10/(1-E10)) | H10: =IF(OR(G10="",D10=""),"",(G10-D10)/G10) | I10: =IF(OR(H10="",E10=""),"",IF(H10<E10,"LOW","OK"))
B11: Cappuccino | F11: =IF(OR(D11="",E11=""),"",D11/(1-E11)) | H11: =IF(OR(G11="",D11=""),"",(G11-D11)/G11) | I11: =IF(OR(H11="",E11=""),"",IF(H11<E11,"LOW","OK"))
B12: Draught beer | F12: =IF(OR(D12="",E12=""),"",D12/(1-E12)) | H12: =IF(OR(G12="",D12=""),"",(G12-D12)/G12) | I12: =IF(OR(H12="",E12=""),"",IF(H12<E12,"LOW","OK"))
F13: =IF(OR(D13="",E13=""),"",D13/(1-E13)) | H13: =IF(OR(G13="",D13=""),"",(G13-D13)/G13) | I13: =IF(OR(H13="",E13=""),"",IF(H13<E13,"LOW","OK"))
F14: =IF(OR(D14="",E14=""),"",D14/(1-E14)) | H14: =IF(OR(G14="",D14=""),"",(G14-D14)/G14) | I14: =IF(OR(H14="",E14=""),"",IF(H14<E14,"LOW","OK"))
F15: =IF(OR(D15="",E15=""),"",D15/(1-E15)) | H15: =IF(OR(G15="",D15=""),"",(G15-D15)/G15) | I15: =IF(OR(H15="",E15=""),"",IF(H15<E15,"LOW","OK"))
F16: =IF(OR(D16="",E16=""),"",D16/(1-E16)) | H16: =IF(OR(G16="",D16=""),"",(G16-D16)/G16) | I16: =IF(OR(H16="",E16=""),"",IF(H16<E16,"LOW","OK"))
F17: =IF(OR(D17="",E17=""),"",D17/(1-E17)) | H17: =IF(OR(G17="",D17=""),"",(G17-D17)/G17) | I17: =IF(OR(H17="",E17=""),"",IF(H17<E17,"LOW","OK"))
F18: =IF(OR(D18="",E18=""),"",D18/(1-E18)) | H18: =IF(OR(G18="",D18=""),"",(G18-D18)/G18) | I18: =IF(OR(H18="",E18=""),"",IF(H18<E18,"LOW","OK"))
F19: =IF(OR(D19="",E19=""),"",D19/(1-E19)) | H19: =IF(OR(G19="",D19=""),"",(G19-D19)/G19) | I19: =IF(OR(H19="",E19=""),"",IF(H19<E19,"LOW","OK"))
F20: =IF(OR(D20="",E20=""),"",D20/(1-E20)) | H20: =IF(OR(G20="",D20=""),"",(G20-D20)/G20) | I20: =IF(OR(H20="",E20=""),"",IF(H20<E20,"LOW","OK"))
F21: =IF(OR(D21="",E21=""),"",D21/(1-E21)) | H21: =IF(OR(G21="",D21=""),"",(G21-D21)/G21) | I21: =IF(OR(H21="",E21=""),"",IF(H21<E21,"LOW","OK"))
F22: =IF(OR(D22="",E22=""),"",D22/(1-E22)) | H22: =IF(OR(G22="",D22=""),"",(G22-D22)/G22) | I22: =IF(OR(H22="",E22=""),"",IF(H22<E22,"LOW","OK"))
F23: =IF(OR(D23="",E23=""),"",D23/(1-E23)) | H23: =IF(OR(G23="",D23=""),"",(G23-D23)/G23) | I23: =IF(OR(H23="",E23=""),"",IF(H23<E23,"LOW","OK"))
F24: =IF(OR(D24="",E24=""),"",D24/(1-E24)) | H24: =IF(OR(G24="",D24=""),"",(G24-D24)/G24) | I24: =IF(OR(H24="",E24=""),"",IF(H24<E24,"LOW","OK"))
... F29: =IF(OR(D29="",E29=""),"",D29/(1-E29)) | H29: =IF(OR(G29="",D29=""),"",(G29-D29)/G29) | I29: =IF(OR(H29="",E29=""),"",IF(H29<E29,"LOW","OK"))
B30: Average real margin | H30: =IFERROR(AVERAGEIF(H8:H29,"<>",H8:H29),0)
B31: Items below target | H31: =COUNTIF(I8:I29,"LOW")

Sheet 05 · Stock
B1: Stock
B2: Usage and loss value
B5: Business name
B6: Period
B7: Loss value is calculated automatically. High losses are highlighted — act on leaks.
B8: Item | C8: Unit | D8: Opening | E8: Purchases | F8: Closing | G8: Losses (qty) | H8: Unit price € | I8: Value — losses €
B9: Draught beer | I9: =IF(OR(G9="",H9=""),"",G9*H9)
B10: House red wine | I10: =IF(OR(G10="",H10=""),"",G10*H10)
B11: Fresh fish | I11: =IF(OR(G11="",H11=""),"",G11*H11)
B12: Rib-eye steak | I12: =IF(OR(G12="",H12=""),"",G12*H12)
B13: Milk | I13: =IF(OR(G13="",H13=""),"",G13*H13)
I14: =IF(OR(G14="",H14=""),"",G14*H14)
I15: =IF(OR(G15="",H15=""),"",G15*H15)
I16: =IF(OR(G16="",H16=""),"",G16*H16)
I17: =IF(OR(G17="",H17=""),"",G17*H17)
I18: =IF(OR(G18="",H18=""),"",G18*H18)
I19: =IF(OR(G19="",H19=""),"",G19*H19)
I20: =IF(OR(G20="",H20=""),"",G20*H20)
I21: =IF(OR(G21="",H21=""),"",G21*H21)
I22: =IF(OR(G22="",H22=""),"",G22*H22)
I23: =IF(OR(G23="",H23=""),"",G23*H23)
I24: =IF(OR(G24="",H24=""),"",G24*H24)
I25: =IF(OR(G25="",H25=""),"",G25*H25)
I26: =IF(OR(G26="",H26=""),"",G26*H26)
B27: Losses — total | I27: =SUM(I9:I26)

Sheet 06 · Rota
B1: Rota
B2: Shifts and labour cost share
B5: Business name
B6: Week of
B7: Revenue plan €
B8: Cost = hours × rate. Target for this sector is usually ~35% of revenue.
B9: Role | C9: Position | D9: Day | E9: From | F9: To | G9: Hours | H9: Rate €/h | I9: Cost €
I10: =IF(OR(G10="",H10=""),"",G10*H10)
I11: =IF(OR(G11="",H11=""),"",G11*H11)
I12: =IF(OR(G12="",H12=""),"",G12*H12)
I13: =IF(OR(G13="",H13=""),"",G13*H13)
I14: =IF(OR(G14="",H14=""),"",G14*H14)
I15: =IF(OR(G15="",H15=""),"",G15*H15)
I16: =IF(OR(G16="",H16=""),"",G16*H16)
I17: =IF(OR(G17="",H17=""),"",G17*H17)
I18: =IF(OR(G18="",H18=""),"",G18*H18)
I19: =IF(OR(G19="",H19=""),"",G19*H19)
I20: =IF(OR(G20="",H20=""),"",G20*H20)
I21: =IF(OR(G21="",H21=""),"",G21*H21)
... I29: =IF(OR(G29="",H29=""),"",G29*H29)
B30: Total labour cost | I30: =SUM(I10:I29)
B31: Labour as % of revenue | I31: =IF(C7="","",I30/C7)

Sheet 07 · Takings
B1: Takings
B2: Daily takings and cash-up
B5: Business name
B6: Month
B7: Sources: Z-reading · cash · cards. Difference = (cash + cards) − Z-reading; non-zero values are highlighted.
B8: Date | C8: Z-reading € | D8: Cash € | E8: Cards € | F8: Deposit € | G8: Counted total € | H8: Difference € | I8: Checked by
G9: =IF(AND(D9="",E9=""),"",D9+E9) | H9: =IF(OR(C9="",G9=""),"",G9-C9)
G10: =IF(AND(D10="",E10=""),"",D10+E10) | H10: =IF(OR(C10="",G10=""),"",G10-C10)
G11: =IF(AND(D11="",E11=""),"",D11+E11) | H11: =IF(OR(C11="",G11=""),"",G11-C11)
G12: =IF(AND(D12="",E12=""),"",D12+E12) | H12: =IF(OR(C12="",G12=""),"",G12-C12)
G13: =IF(AND(D13="",E13=""),"",D13+E13) | H13: =IF(OR(C13="",G13=""),"",G13-C13)
G14: =IF(AND(D14="",E14=""),"",D14+E14) | H14: =IF(OR(C14="",G14=""),"",G14-C14)
G15: =IF(AND(D15="",E15=""),"",D15+E15) | H15: =IF(OR(C15="",G15=""),"",G15-C15)
G16: =IF(AND(D16="",E16=""),"",D16+E16) | H16: =IF(OR(C16="",G16=""),"",G16-C16)
G17: =IF(AND(D17="",E17=""),"",D17+E17) | H17: =IF(OR(C17="",G17=""),"",G17-C17)
G18: =IF(AND(D18="",E18=""),"",D18+E18) | H18: =IF(OR(C18="",G18=""),"",G18-C18)
G19: =IF(AND(D19="",E19=""),"",D19+E19) | H19: =IF(OR(C19="",G19=""),"",G19-C19)
G20: =IF(AND(D20="",E20=""),"",D20+E20) | H20: =IF(OR(C20="",G20=""),"",G20-C20)
... G39: =IF(AND(D39="",E39=""),"",D39+E39) | H39: =IF(OR(C39="",G39=""),"",G39-C39)
B40: Total (year) | C40: =SUM(C9:C39) | H40: =SUM(H9:H39)

Sheet 08 · Training
B1: Training
B2: Training matrix — proof before a shift
B5: Business name
B6: Enter the date completed (DD/MM/YYYY). Empty cell = missing training before work.
B7: Employee | C7: Start | D7: Induction | E7: Manual handling | F7: Food hygiene | G7: Allergens | H7: Fire safety | I7: H&S / first aid | J7: Refresher
B25: Note: health & safety law requires staff to be trained for their job — keep the matrix current.
